{
  "openapi": "3.0.1",
  "info": {
    "title": "Health & Fitness API",
    "version": "v1"
  },
  "paths": {
    "/api/Auth/register": {
      "post": {
        "tags": [
          "Auth"
        ],
        "requestBody": {
          "content": {
            "application/json": {
              "schema": {
                "$ref": "#/components/schemas/RegisterUser"
              }
            },
            "text/json": {
              "schema": {
                "$ref": "#/components/schemas/RegisterUser"
              }
            },
            "application/*+json": {
              "schema": {
                "$ref": "#/components/schemas/RegisterUser"
              }
            }
          }
        },
        "responses": {
          "200": {
            "description": "OK"
          }
        }
      }
    },
    "/api/Auth/login": {
      "post": {
        "tags": [
          "Auth"
        ],
        "requestBody": {
          "content": {
            "application/json": {
              "schema": {
                "$ref": "#/components/schemas/LoginUser"
              }
            },
            "text/json": {
              "schema": {
                "$ref": "#/components/schemas/LoginUser"
              }
            },
            "application/*+json": {
              "schema": {
                "$ref": "#/components/schemas/LoginUser"
              }
            }
          }
        },
        "responses": {
          "200": {
            "description": "OK"
          }
        }
      }
    },
    "/api/CalorieLog": {
      "get": {
        "tags": [
          "CalorieLog"
        ],
        "responses": {
          "200": {
            "description": "OK",
            "content": {
              "text/plain": {
                "schema": {
                  "type": "array",
                  "items": {
                    "$ref": "#/components/schemas/CalorieLog"
                  }
                }
              },
              "application/json": {
                "schema": {
                  "type": "array",
                  "items": {
                    "$ref": "#/components/schemas/CalorieLog"
                  }
                }
              },
              "text/json": {
                "schema": {
                  "type": "array",
                  "items": {
                    "$ref": "#/components/schemas/CalorieLog"
                  }
                }
              }
            }
          }
        }
      },
      "post": {
        "tags": [
          "CalorieLog"
        ],
        "requestBody": {
          "content": {
            "application/json": {
              "schema": {
                "$ref": "#/components/schemas/CalorieLog"
              }
            },
            "text/json": {
              "schema": {
                "$ref": "#/components/schemas/CalorieLog"
              }
            },
            "application/*+json": {
              "schema": {
                "$ref": "#/components/schemas/CalorieLog"
              }
            }
          }
        },
        "responses": {
          "200": {
            "description": "OK"
          }
        }
      }
    },
    "/api/CalorieLog/{id}": {
      "get": {
        "tags": [
          "CalorieLog"
        ],
        "parameters": [
          {
            "name": "id",
            "in": "path",
            "required": true,
            "schema": {
              "type": "integer",
              "format": "int32"
            }
          }
        ],
        "responses": {
          "200": {
            "description": "OK",
            "content": {
              "text/plain": {
                "schema": {
                  "$ref": "#/components/schemas/CalorieLog"
                }
              },
              "application/json": {
                "schema": {
                  "$ref": "#/components/schemas/CalorieLog"
                }
              },
              "text/json": {
                "schema": {
                  "$ref": "#/components/schemas/CalorieLog"
                }
              }
            }
          }
        }
      },
      "put": {
        "tags": [
          "CalorieLog"
        ],
        "parameters": [
          {
            "name": "id",
            "in": "path",
            "required": true,
            "schema": {
              "type": "integer",
              "format": "int32"
            }
          }
        ],
        "requestBody": {
          "content": {
            "application/json": {
              "schema": {
                "$ref": "#/components/schemas/CalorieLog"
              }
            },
            "text/json": {
              "schema": {
                "$ref": "#/components/schemas/CalorieLog"
              }
            },
            "application/*+json": {
              "schema": {
                "$ref": "#/components/schemas/CalorieLog"
              }
            }
          }
        },
        "responses": {
          "200": {
            "description": "OK"
          }
        }
      },
      "delete": {
        "tags": [
          "CalorieLog"
        ],
        "parameters": [
          {
            "name": "id",
            "in": "path",
            "required": true,
            "schema": {
              "type": "integer",
              "format": "int32"
            }
          }
        ],
        "responses": {
          "200": {
            "description": "OK"
          }
        }
      }
    },
    "/api/User/register": {
      "post": {
        "tags": [
          "User"
        ],
        "requestBody": {
          "content": {
            "application/json": {
              "schema": {
                "$ref": "#/components/schemas/User"
              }
            },
            "text/json": {
              "schema": {
                "$ref": "#/components/schemas/User"
              }
            },
            "application/*+json": {
              "schema": {
                "$ref": "#/components/schemas/User"
              }
            }
          }
        },
        "responses": {
          "200": {
            "description": "OK"
          }
        }
      }
    },
    "/api/User/login": {
      "post": {
        "tags": [
          "User"
        ],
        "requestBody": {
          "content": {
            "application/json": {
              "schema": {
                "$ref": "#/components/schemas/User"
              }
            },
            "text/json": {
              "schema": {
                "$ref": "#/components/schemas/User"
              }
            },
            "application/*+json": {
              "schema": {
                "$ref": "#/components/schemas/User"
              }
            }
          }
        },
        "responses": {
          "200": {
            "description": "OK"
          }
        }
      }
    },
    "/WeatherForecast": {
      "get": {
        "tags": [
          "WeatherForecast"
        ],
        "operationId": "GetWeatherForecast",
        "responses": {
          "200": {
            "description": "OK",
            "content": {
              "text/plain": {
                "schema": {
                  "type": "array",
                  "items": {
                    "$ref": "#/components/schemas/WeatherForecast"
                  }
                }
              },
              "application/json": {
                "schema": {
                  "type": "array",
                  "items": {
                    "$ref": "#/components/schemas/WeatherForecast"
                  }
                }
              },
              "text/json": {
                "schema": {
                  "type": "array",
                  "items": {
                    "$ref": "#/components/schemas/WeatherForecast"
                  }
                }
              }
            }
          }
        }
      }
    },
    "/api/Workout": {
      "get": {
        "tags": [
          "Workout"
        ],
        "responses": {
          "200": {
            "description": "OK",
            "content": {
              "text/plain": {
                "schema": {
                  "type": "array",
                  "items": {
                    "$ref": "#/components/schemas/Workout"
                  }
                }
              },
              "application/json": {
                "schema": {
                  "type": "array",
                  "items": {
                    "$ref": "#/components/schemas/Workout"
                  }
                }
              },
              "text/json": {
                "schema": {
                  "type": "array",
                  "items": {
                    "$ref": "#/components/schemas/Workout"
                  }
                }
              }
            }
          }
        }
      },
      "post": {
        "tags": [
          "Workout"
        ],
        "requestBody": {
          "content": {
            "application/json": {
              "schema": {
                "$ref": "#/components/schemas/Workout"
              }
            },
            "text/json": {
              "schema": {
                "$ref": "#/components/schemas/Workout"
              }
            },
            "application/*+json": {
              "schema": {
                "$ref": "#/components/schemas/Workout"
              }
            }
          }
        },
        "responses": {
          "200": {
            "description": "OK"
          }
        }
      }
    },
    "/api/Workout/{id}": {
      "get": {
        "tags": [
          "Workout"
        ],
        "parameters": [
          {
            "name": "id",
            "in": "path",
            "required": true,
            "schema": {
              "type": "integer",
              "format": "int32"
            }
          }
        ],
        "responses": {
          "200": {
            "description": "OK"
          }
        }
      },
      "put": {
        "tags": [
          "Workout"
        ],
        "parameters": [
          {
            "name": "id",
            "in": "path",
            "required": true,
            "schema": {
              "type": "integer",
              "format": "int32"
            }
          }
        ],
        "requestBody": {
          "content": {
            "application/json": {
              "schema": {
                "$ref": "#/components/schemas/Workout"
              }
            },
            "text/json": {
              "schema": {
                "$ref": "#/components/schemas/Workout"
              }
            },
            "application/*+json": {
              "schema": {
                "$ref": "#/components/schemas/Workout"
              }
            }
          }
        },
        "responses": {
          "200": {
            "description": "OK"
          }
        }
      },
      "delete": {
        "tags": [
          "Workout"
        ],
        "parameters": [
          {
            "name": "id",
            "in": "path",
            "required": true,
            "schema": {
              "type": "integer",
              "format": "int32"
            }
          }
        ],
        "responses": {
          "200": {
            "description": "OK"
          }
        }
      }
    }
  },
  "components": {
    "schemas": {
      "CalorieLog": {
        "type": "object",
        "properties": {
          "id": {
            "type": "integer",
            "format": "int32"
          },
          "userId": {
            "type": "string",
            "nullable": true
          },
          "foodItem": {
            "type": "string",
            "nullable": true
          },
          "calories": {
            "type": "integer",
            "format": "int32"
          },
          "date": {
            "type": "string",
            "format": "date-time"
          }
        },
        "additionalProperties": false
      },
      "LoginUser": {
        "required": [
          "email",
          "password"
        ],
        "type": "object",
        "properties": {
          "email": {
            "minLength": 1,
            "type": "string",
            "format": "email"
          },
          "password": {
            "minLength": 1,
            "type": "string"
          }
        },
        "additionalProperties": false
      },
      "RegisterUser": {
        "required": [
          "email",
          "name",
          "password"
        ],
        "type": "object",
        "properties": {
          "name": {
            "minLength": 1,
            "type": "string"
          },
          "email": {
            "minLength": 1,
            "type": "string",
            "format": "email"
          },
          "password": {
            "minLength": 6,
            "type": "string"
          }
        },
        "additionalProperties": false
      },
      "User": {
        "required": [
          "name"
        ],
        "type": "object",
        "properties": {
          "id": {
            "type": "string",
            "nullable": true
          },
          "userName": {
            "type": "string",
            "nullable": true
          },
          "normalizedUserName": {
            "type": "string",
            "nullable": true
          },
          "email": {
            "type": "string",
            "nullable": true
          },
          "normalizedEmail": {
            "type": "string",
            "nullable": true
          },
          "emailConfirmed": {
            "type": "boolean"
          },
          "passwordHash": {
            "type": "string",
            "nullable": true
          },
          "securityStamp": {
            "type": "string",
            "nullable": true
          },
          "concurrencyStamp": {
            "type": "string",
            "nullable": true
          },
          "phoneNumber": {
            "type": "string",
            "nullable": true
          },
          "phoneNumberConfirmed": {
            "type": "boolean"
          },
          "twoFactorEnabled": {
            "type": "boolean"
          },
          "lockoutEnd": {
            "type": "string",
            "format": "date-time",
            "nullable": true
          },
          "lockoutEnabled": {
            "type": "boolean"
          },
          "accessFailedCount": {
            "type": "integer",
            "format": "int32"
          },
          "name": {
            "minLength": 1,
            "type": "string"
          }
        },
        "additionalProperties": false
      },
      "WeatherForecast": {
        "type": "object",
        "properties": {
          "date": {
            "type": "string",
            "format": "date"
          },
          "temperatureC": {
            "type": "integer",
            "format": "int32"
          },
          "temperatureF": {
            "type": "integer",
            "format": "int32",
            "readOnly": true
          },
          "summary": {
            "type": "string",
            "nullable": true
          }
        },
        "additionalProperties": false
      },
      "Workout": {
        "type": "object",
        "properties": {
          "id": {
            "type": "integer",
            "format": "int32"
          },
          "userId": {
            "type": "string",
            "nullable": true
          },
          "workoutType": {
            "type": "string",
            "nullable": true
          },
          "duration": {
            "type": "integer",
            "format": "int32"
          },
          "caloriesBurned": {
            "type": "integer",
            "format": "int32"
          },
          "date": {
            "type": "string",
            "format": "date-time"
          }
        },
        "additionalProperties": false
      }
    },
    "securitySchemes": {
      "Bearer": {
        "type": "http",
        "scheme": "Bearer",
        "bearerFormat": "JWT"
      }
    }
  },
  "security": [
    {
      "Bearer": [ ]
    }
  ]
}